init_service_auto/__init__.py
init_service_auto/agent.cpython-311-x86_64-linux-gnu.so
init_service_auto/wrapper.py
init_service_auto-0.2.1.dist-info/METADATA
init_service_auto-0.2.1.dist-info/WHEEL
init_service_auto-0.2.1.dist-info/entry_points.txt
init_service_auto-0.2.1.dist-info/top_level.txt
init_service_auto-0.2.1.dist-info/RECORD
