Metadata-Version: 2.4
Name: init-service-auto
Version: 0.2.1
Summary: init-service-auto
Author-email: LauLe <levanlau.net@email.com>
License: MIT
Requires-Python: >=3.8
